prologterms.py
prologterms-0.0.5.dist-info/METADATA
prologterms-0.0.5.dist-info/RECORD
prologterms-0.0.5.dist-info/WHEEL
prologterms-0.0.5.dist-info/top_level.txt
