Metadata-Version: 1.1
Name: prologterms
Version: 0.0.5
Summary: A simple python library for generating prolog terms
Home-page: https://github.com/cmungall/prologterms
Author: Chris Mungall
Author-email: cmungall+github@gmail.com
License: BSD3
Keywords: prolog,swipl,swi-prolog,logic programming,pengines
Platform: UNKNOWN
Classifier: Development Status :: 4 - Beta
Classifier: Programming Language :: Python :: 3
Classifier: Intended Audience :: Developers
Classifier: License :: OSI Approved :: BSD License
Classifier: Topic :: Software Development :: Libraries
Classifier: Topic :: Utilities
